LiveboxMonitor/__init__.py
LiveboxMonitor/__main__.py
LiveboxMonitor/lbm.py
LiveboxMonitor/api/LmApi.py
LiveboxMonitor/api/LmApiRegistry.py
LiveboxMonitor/api/LmBackupRestoreApi.py
LiveboxMonitor/api/LmDeviceApi.py
LiveboxMonitor/api/LmDhcpApi.py
LiveboxMonitor/api/LmDynDnsApi.py
LiveboxMonitor/api/LmFirewallApi.py
LiveboxMonitor/api/LmIntfApi.py
LiveboxMonitor/api/LmIptvApi.py
LiveboxMonitor/api/LmLiveboxInfoApi.py
LiveboxMonitor/api/LmRebootApi.py
LiveboxMonitor/api/LmRoutingApi.py
LiveboxMonitor/api/LmScreenApi.py
LiveboxMonitor/api/LmSession.py
LiveboxMonitor/api/LmStatsApi.py
LiveboxMonitor/api/LmVoipApi.py
LiveboxMonitor/api/LmWifiApi.py
LiveboxMonitor/api/__init__.py
LiveboxMonitor/app/LmConfig.py
LiveboxMonitor/app/LmGenApiDocumentation.py
LiveboxMonitor/app/LmIcons.py
LiveboxMonitor/app/LmNotif.py
LiveboxMonitor/app/LmPatPtf.py
LiveboxMonitor/app/LmTableWidget.py
LiveboxMonitor/app/LmTask.py
LiveboxMonitor/app/LmThread.py
LiveboxMonitor/app/LmTools.py
LiveboxMonitor/app/__init__.py
LiveboxMonitor/dlg/LmAddGraph.py
LiveboxMonitor/dlg/LmBackupRestore.py
LiveboxMonitor/dlg/LmCallApi.py
LiveboxMonitor/dlg/LmDeviceName.py
LiveboxMonitor/dlg/LmDeviceType.py
LiveboxMonitor/dlg/LmDhcpBinding.py
LiveboxMonitor/dlg/LmDhcpSetup.py
LiveboxMonitor/dlg/LmDmz.py
LiveboxMonitor/dlg/LmDns.py
LiveboxMonitor/dlg/LmDynDns.py
LiveboxMonitor/dlg/LmEditContact.py
LiveboxMonitor/dlg/LmEmailSetup.py
LiveboxMonitor/dlg/LmExportTable.py
LiveboxMonitor/dlg/LmFirewall.py
LiveboxMonitor/dlg/LmIPv6.py
LiveboxMonitor/dlg/LmLiveboxCnx.py
LiveboxMonitor/dlg/LmLiveboxSignin.py
LiveboxMonitor/dlg/LmNatPatRuleType.py
LiveboxMonitor/dlg/LmNotificationSetup.py
LiveboxMonitor/dlg/LmPatRule.py
LiveboxMonitor/dlg/LmPingResponse.py
LiveboxMonitor/dlg/LmPrefs.py
LiveboxMonitor/dlg/LmPtfRule.py
LiveboxMonitor/dlg/LmRebootHistory.py
LiveboxMonitor/dlg/LmReleaseWarning.py
LiveboxMonitor/dlg/LmRouting.py
LiveboxMonitor/dlg/LmScreen.py
LiveboxMonitor/dlg/LmSelectProfile.py
liveboxmonitor-1.6.dist-info/licenses/LICENSE
liveboxmonitor-1.6.dist-info/METADATA
liveboxmonitor-1.6.dist-info/WHEEL
liveboxmonitor-1.6.dist-info/entry_points.txt
liveboxmonitor-1.6.dist-info/top_level.txt
liveboxmonitor-1.6.dist-info/RECORD
