Metadata-Version: 2.4
Name: LiveboxMonitor
Version: 1.6
Summary: Advanced graphical user interface to control Livebox 4, 5, 6, 7, W7 & S
Author-email: Pierre Dor <dorpierre@orange.fr>
License: MIT License
Project-URL: homepage, https://github.com/p-dor/LiveboxMonitor
Project-URL: documentation, https://p-dor.github.io/LiveboxMonitor
Project-URL: source, https://github.com/p-dor/LiveboxMonitor
Project-URL: issues, https://github.com/p-dor/LiveboxMonitor/issues
Project-URL: changelog, https://github.com/p-dor/LiveboxMonitor/releases
Project-URL: discussions, https://github.com/p-dor/LiveboxMonitor/discussions
Project-URL: funding, https://www.paypal.com/donate/?hosted_button_id=U7CLQM3WGTUEJ&locale.x=fr_FR
Keywords: livebox,sysbus,ui,monitoring,traffic
Classifier: License :: OSI Approved :: MIT License
Classifier: Development Status :: 5 - Production/Stable
Classifier: Operating System :: OS Independent
Classifier: Programming Language :: Python
Classifier: Programming Language :: Python :: 3
Classifier: Topic :: System :: Monitoring
Classifier: Topic :: System :: Networking :: Monitoring
Classifier: Topic :: Home Automation
Requires-Python: >=3.10
License-File: LICENSE
Requires-Dist: PyQt6
Requires-Dist: requests
Requires-Dist: python-dateutil
Requires-Dist: cryptography
Requires-Dist: pyqtgraph
Requires-Dist: wakepy
Provides-Extra: dev
Dynamic: license-file
